django_pays/__init__.py
django_pays/admin.py
django_pays/models.py
django_pays/urls.py
django_pays/views.py
django_pays/migrations/0001_initial.py
django_pays/migrations/__init__.py
django_pays/templatetags/__init__.py
django_pays/templatetags/pays.py
django_pays-0.3.0.dist-info/licenses/LICENSE
django_pays_demo/__init__.py
django_pays_demo/settings.py
django_pays_demo/urls.py
django_pays_demo/wsgi.py
django_pays_demo/demoapp/__init__.py
django_pays_demo/demoapp/admin.py
django_pays_demo/demoapp/models.py
django_pays_demo/demoapp/migrations/0001_initial.py
django_pays_demo/demoapp/migrations/__init__.py
django_pays-0.3.0.dist-info/METADATA
django_pays-0.3.0.dist-info/WHEEL
django_pays-0.3.0.dist-info/top_level.txt
django_pays-0.3.0.dist-info/RECORD
